LICENSE
README.md
setup.py
beautiful_tensors/__init__.py
beautiful_tensors.egg-info/PKG-INFO
beautiful_tensors.egg-info/SOURCES.txt
beautiful_tensors.egg-info/dependency_links.txt
beautiful_tensors.egg-info/requires.txt
beautiful_tensors.egg-info/top_level.txt